tests/__init__.py
tests/test_VickyEditor.py
vicky-mod-editor/BlockUtils.py
vicky-mod-editor/Country.py
vicky-mod-editor/DataReader.py
vicky-mod-editor/DataWriter.py
vicky-mod-editor/State.py
vicky-mod-editor/VickyEditor.py
vicky-mod-editor/__init__.py
vicky-mod-editor/utils.py
vicky_mod_editor/BlockUtils.py
vicky_mod_editor/Country.py
vicky_mod_editor/DataReader.py
vicky_mod_editor/DataWriter.py
vicky_mod_editor/State.py
vicky_mod_editor/VickyEditor.py
vicky_mod_editor/__init__.py
vicky_mod_editor/utils.py
vicky_mod_editor-0.1.3.dist-info/METADATA
vicky_mod_editor-0.1.3.dist-info/WHEEL
vicky_mod_editor-0.1.3.dist-info/entry_points.txt
vicky_mod_editor-0.1.3.dist-info/top_level.txt
vicky_mod_editor-0.1.3.dist-info/RECORD
