Metadata-Version: 2.1
Name: vicky-mod-editor
Version: 0.1.3
Summary: Vicky Mod Editor
Home-page: https://github.com/supamap/vicky-mod-editor
Author: supamap
License: UNKNOWN
Platform: UNKNOWN
Requires-Dist: ClauseWizard
Requires-Dist: pyparsing
